pyresparser/CHANGELOG.md
pyresparser/__init__.py
pyresparser/command_line.py
pyresparser/constants.py
pyresparser/custom_t.py
pyresparser/custom_train.py
pyresparser/meta.json
pyresparser/requirements.txt
pyresparser/resume_parser.py
pyresparser/skills.csv
pyresparser/tokenizer
pyresparser/utils.py
pyresparser/__pycache__/__init__.cpython-36.pyc
pyresparser/__pycache__/command_line.cpython-36.pyc
pyresparser/__pycache__/constants.cpython-36.pyc
pyresparser/__pycache__/resume_parser.cpython-36.pyc
pyresparser/__pycache__/utils.cpython-36.pyc
pyresparser/ner/cfg
pyresparser/ner/model
pyresparser/ner/moves
pyresparser/vocab/key2row
pyresparser/vocab/lexemes.bin
pyresparser/vocab/strings.json
pyresparser/vocab/vectors
pyresparser-1.0.6.dist-info/LICENSE
pyresparser-1.0.6.dist-info/METADATA
pyresparser-1.0.6.dist-info/WHEEL
pyresparser-1.0.6.dist-info/entry_points.txt
pyresparser-1.0.6.dist-info/top_level.txt
pyresparser-1.0.6.dist-info/RECORD
