Metadata-Version: 1.1
Name: pyresparser
Version: 1.0.6
Summary: A simple resume parser used for extracting information from resumes
Home-page: https://github.com/OmkarPathak/pyresparser
Author: Omkar Pathak
Author-email: omkarpathak27@gmail.com
License: GPL-3.0
Platform: UNKNOWN
Classifier: Intended Audience :: Developers
Classifier: Topic :: Software Development :: Libraries
Classifier: License :: OSI Approved :: GNU General Public License v3 (GPLv3)
Classifier: Programming Language :: Python :: 3
Classifier: Programming Language :: Python :: 3.3
Classifier: Programming Language :: Python :: 3.4
Classifier: Programming Language :: Python :: 3.5
Classifier: Programming Language :: Python :: 3.6
Classifier: Programming Language :: Python :: 3.7
